cmakelang/__init__.py
cmakelang/annotate.py
cmakelang/common.py
cmakelang/config_util.py
cmakelang/configuration.py
cmakelang/ctest_to.py
cmakelang/genparsers.py
cmakelang/markup.py
cmakelang/markup_tests.py
cmakelang/render.py
cmakelang/tests.py
cmakelang/format/__init__.py
cmakelang/format/__main__.py
cmakelang/format/formatter.py
cmakelang/format/invocation_tests.py
cmakelang/format/layout_tests.py
cmakelang/lex/__init__.py
cmakelang/lex/__main__.py
cmakelang/lex/tests.py
cmakelang/lint/__init__.py
cmakelang/lint/__main__.py
cmakelang/lint/basic_checker.py
cmakelang/lint/gendocs.py
cmakelang/lint/lint_util.py
cmakelang/lint/lintdb.py
cmakelang/parse/__init__.py
cmakelang/parse/additional_nodes.py
cmakelang/parse/argument_nodes.py
cmakelang/parse/body_nodes.py
cmakelang/parse/common.py
cmakelang/parse/printer.py
cmakelang/parse/properties.py
cmakelang/parse/simple_nodes.py
cmakelang/parse/statement_node.py
cmakelang/parse/tests.py
cmakelang/parse/util.py
cmakelang/parse/variables.py
cmakelang/parse/funs/__init__.py
cmakelang/parse/funs/add_executable.py
cmakelang/parse/funs/add_library.py
cmakelang/parse/funs/add_xxx.py
cmakelang/parse/funs/break.py
cmakelang/parse/funs/deprecated.py
cmakelang/parse/funs/external_project.py
cmakelang/parse/funs/fetch_content.py
cmakelang/parse/funs/file.py
cmakelang/parse/funs/foreach.py
cmakelang/parse/funs/install.py
cmakelang/parse/funs/list.py
cmakelang/parse/funs/miscellaneous.py
cmakelang/parse/funs/random.py
cmakelang/parse/funs/set.py
cmakelang/parse/funs/set_target_properties.py
cmakelang/parse/funs/standard_builtins.py
cmakelang/parse/funs/standard_funs.py
cmakelang/parse/funs/standard_modules.py
cmakelang/templates/layout.html.tpl
cmakelang/templates/style.css
cmakelang-0.6.13.dist-info/LICENSE
cmakelang-0.6.13.dist-info/METADATA
cmakelang-0.6.13.dist-info/WHEEL
cmakelang-0.6.13.dist-info/entry_points.txt
cmakelang-0.6.13.dist-info/top_level.txt
cmakelang-0.6.13.dist-info/RECORD
