Metadata-Version: 2.1
Name: cmakelang
Version: 0.6.13
Summary: Language tools for cmake (format, lint, etc)
Home-page: https://github.com/cheshirekow/cmakelang
Author: Josh Bialkowski
Author-email: josh.bialkowski@gmail.com
License: GPLv3
Download-URL: https://github.com/cheshirekow/cmakelang/archive/0.6.13.tar.gz
Keywords: cmake,format
Platform: UNKNOWN
Classifier: Development Status :: 3 - Alpha
Classifier: Intended Audience :: Developers
Classifier: License :: OSI Approved :: GNU General Public License v3 (GPLv3)
Provides-Extra: YAML
Provides-Extra: html-gen
